{
  "restaurants": [
    {
      "name": "dominoz",
      "address": "ahmedabad",
      "id": 1
    },
    {
      "name": "honest",
      "address": "maninagar",
      "id": 2
    },
    {
      "name": "City Corner",
      "address": "xyz",
      "id": 4
    }
  ],
  "users": [
    {
      "name": "Nirav",
      "password": "abcd123",
      "email": "niravpatidar37@gmail.com",
      "id": 1
    },
    {
      "name": "Nirav",
      "password": "abcd123",
      "email": "niravpatidar37@gmail.com",
      "id": 2
    },
    {
      "name": "jay",
      "password": "jay123",
      "email": "jay@gmail.com",
      "id": 3
    },
    {
      "name": "jay",
      "password": "jay123",
      "email": "jay@gmail.com",
      "id": 4
    },
    {
      "name": "niravpatidar7@gmail.com",
      "password": "abcd123",
      "email": "nirav@gmail.com",
      "id": 5
    },
    {
      "name": "abcd",
      "password": "qwerty",
      "email": "abcd@gmail.com",
      "id": 6
    }
  ]
}